{
  "_format": "hh-sol-cache-2",
  "files": {
    "E:\\Sidrah\\VS Code\\Voting System dApp\\contracts\\VotingSystem.sol": {
      "lastModificationDate": 1703078963094,
      "contentHash": "3bc3bd1a6dc3a9f76b11147aacb6cb71",
      "sourceName": "contracts/VotingSystem.sol",
      "solcConfig": {
        "version": "0.8.19",
        "settings": {
          "optimizer": {
            "enabled": false,
            "runs": 200
          },
          "outputSelection": {
            "*": {
              "*": [
                "abi",
                "evm.bytecode",
                "evm.deployedBytecode",
                "evm.methodIdentifiers",
                "metadata"
              ],
              "": [
                "ast"
              ]
            }
          }
        }
      },
      "imports": [],
      "versionPragmas": [
        ">=0.7.0 <0.9.0"
      ],
      "artifacts": [
        "Voting"
      ]
    }
  }
}
